{"format":2,"version":"5.0.4","globals":"6f970bb3fd818c0086bb8745517713d8","files":{"command_py":{"hash":"ae62ede2a979e5fe2319f750b21305c6","index":{"nums":[1,644,0,407,0,0,0],"html_filename":"command_py.html","relative_filename":"command.py"}},"env_py":{"hash":"79011b0a6233a6494d98689480d28fa8","index":{"nums":[1,38,0,8,0,0,0],"html_filename":"env_py.html","relative_filename":"env.py"}},"graph_py":{"hash":"76291bc8b77b33e701cf02d81ed32845","index":{"nums":[1,194,0,52,0,0,0],"html_filename":"graph_py.html","relative_filename":"graph.py"}},"klee_utils_py":{"hash":"421e9f2105629aa228bce1e716032d21","index":{"nums":[1,62,0,50,0,0,0],"html_filename":"klee_utils_py.html","relative_filename":"klee_utils.py"}},"lang_to_cfg___init___py":{"hash":"475ef7fe695da7287b66d571a49d03f8","index":{"nums":[1,0,0,0,0,0,0],"html_filename":"lang_to_cfg___init___py.html","relative_filename":"lang_to_cfg/__init__.py"}},"lang_to_cfg_cpp_py":{"hash":"867da3dbc2a4d75de361290ca41b47ef","index":{"nums":[1,120,0,100,0,0,0],"html_filename":"lang_to_cfg_cpp_py.html","relative_filename":"lang_to_cfg/cpp.py"}},"lang_to_cfg_java_py":{"hash":"bedfe6dee7e3f4a3bb0185b8396bf5a6","index":{"nums":[1,13,0,7,0,0,0],"html_filename":"lang_to_cfg_java_py.html","relative_filename":"lang_to_cfg/java.py"}},"lang_to_cfg_javaextractor_app_py":{"hash":"804fa5246064088c121b5fbfbaeb88f7","index":{"nums":[1,57,0,46,0,0,0],"html_filename":"lang_to_cfg_javaextractor_app_py.html","relative_filename":"lang_to_cfg/javaextractor/app.py"}},"lang_to_cfg_javaextractor_shell_py":{"hash":"29de7201437944ea6f2c722380a4f582","index":{"nums":[1,64,0,45,0,0,0],"html_filename":"lang_to_cfg_javaextractor_shell_py.html","relative_filename":"lang_to_cfg/javaextractor/shell.py"}},"lang_to_cfg_python_py":{"hash":"ddca5f32e7f24b94858c1829f9c42bd4","index":{"nums":[1,188,0,3,0,0,0],"html_filename":"lang_to_cfg_python_py.html","relative_filename":"lang_to_cfg/python.py"}},"log_py":{"hash":"332db91a8d488e03838da9d638b5ee30","index":{"nums":[1,39,0,2,0,0,0],"html_filename":"log_py.html","relative_filename":"log.py"}},"metric___init___py":{"hash":"fda0ec7bd264db16655cb672f8cdb3d9","index":{"nums":[1,0,0,0,0,0,0],"html_filename":"metric___init___py.html","relative_filename":"metric/__init__.py"}},"metric_cyclomatic_complexity_py":{"hash":"b9cfa7b37128d832b559932195d45cca","index":{"nums":[1,9,0,0,0,0,0],"html_filename":"metric_cyclomatic_complexity_py.html","relative_filename":"metric/cyclomatic_complexity.py"}},"metric_metric_py":{"hash":"8570eb97afdeb7e55552b13d4380c919","index":{"nums":[1,10,0,0,0,0,0],"html_filename":"metric_metric_py.html","relative_filename":"metric/metric.py"}},"metric_npath_complexity_py":{"hash":"87cb584706ab8a47f5998e9834f7893a","index":{"nums":[1,61,0,1,0,0,0],"html_filename":"metric_npath_complexity_py.html","relative_filename":"metric/npath_complexity.py"}},"metric_path_complexity_py":{"hash":"273ab73c6d9af3234b8edc72c9d25380","index":{"nums":[1,91,0,42,0,0,0],"html_filename":"metric_path_complexity_py.html","relative_filename":"metric/path_complexity.py"}},"tests___init___py":{"hash":"d4ca240919c9978006b01078aba0dba7","index":{"nums":[1,0,0,0,0,0,0],"html_filename":"tests___init___py.html","relative_filename":"tests/__init__.py"}},"tests_test_command_py":{"hash":"1e7e80d25f773139322abc66ab6e8bb4","index":{"nums":[1,144,0,1,0,0,0],"html_filename":"tests_test_command_py.html","relative_filename":"tests/test_command.py"}},"tests_test_cpp_py":{"hash":"92413b1c562af78ae7448eaf2c929011","index":{"nums":[1,13,0,6,0,0,0],"html_filename":"tests_test_cpp_py.html","relative_filename":"tests/test_cpp.py"}},"tests_test_cyclomatic_py":{"hash":"26749f1aa18a16cf9cc49a94e77d8a68","index":{"nums":[1,17,0,1,0,0,0],"html_filename":"tests_test_cyclomatic_py.html","relative_filename":"tests/test_cyclomatic.py"}},"tests_test_graph_py":{"hash":"75a1ed9403bb8918d74d81e154ecdd9e","index":{"nums":[1,51,0,2,0,0,0],"html_filename":"tests_test_graph_py.html","relative_filename":"tests/test_graph.py"}},"tests_test_java_py":{"hash":"3e8483abe0d13bc1a746414bb978d6fe","index":{"nums":[1,5,0,1,0,0,0],"html_filename":"tests_test_java_py.html","relative_filename":"tests/test_java.py"}},"tests_test_log_py":{"hash":"056ccf81a07df9422b3fcc58b606ae98","index":{"nums":[1,37,0,2,0,0,0],"html_filename":"tests_test_log_py.html","relative_filename":"tests/test_log.py"}},"tests_test_metrics_py":{"hash":"4ac93d26cab7eed868051e1b1166cfe3","index":{"nums":[1,3,0,1,0,0,0],"html_filename":"tests_test_metrics_py.html","relative_filename":"tests/test_metrics.py"}},"tests_test_npath_py":{"hash":"53ed20c18865ec69c40116a8eab17289","index":{"nums":[1,40,0,1,0,0,0],"html_filename":"tests_test_npath_py.html","relative_filename":"tests/test_npath.py"}},"tests_test_pathcomplexity_py":{"hash":"df1c0b238c1fc48ecd1db50f652a3fe9","index":{"nums":[1,14,0,1,0,0,0],"html_filename":"tests_test_pathcomplexity_py.html","relative_filename":"tests/test_pathcomplexity.py"}},"tests_test_python_py":{"hash":"e900d5efa37e035be07f8ee8e00e28f3","index":{"nums":[1,44,0,1,0,0,0],"html_filename":"tests_test_python_py.html","relative_filename":"tests/test_python.py"}},"tests_test_utils_py":{"hash":"837291723d9cb5282193ab066a46e947","index":{"nums":[1,20,0,1,0,0,0],"html_filename":"tests_test_utils_py.html","relative_filename":"tests/test_utils.py"}},"tests_unit_utils_py":{"hash":"acb3364668509dec53214d694a452a2a","index":{"nums":[1,93,0,68,0,0,0],"html_filename":"tests_unit_utils_py.html","relative_filename":"tests/unit_utils.py"}},"utils_py":{"hash":"d0a561f65dd30a6e678f3aa6c0ae2409","index":{"nums":[1,103,0,63,0,0,0],"html_filename":"utils_py.html","relative_filename":"utils.py"}}}}